authenticating/URLs.py
authenticating/__init__.py
authenticating/authenticatingAPI.py
authenticating/utils/__init__.py
authenticating/utils/decorators.py
authenticating/utils/resources.py
authenticating_python-0.1.3.dist-info/LICENSE
authenticating_python-0.1.3.dist-info/METADATA
authenticating_python-0.1.3.dist-info/WHEEL
authenticating_python-0.1.3.dist-info/top_level.txt
authenticating_python-0.1.3.dist-info/RECORD
