Metadata-Version: 2.1
Name: authenticating-python
Version: 0.1.3
Summary: authenticating.com-python
Home-page: https://github.com/SmokingTheGoaT/authenticating.com-python
Author: SmokingGoaT
Author-email: UNKNOWN
License: MIT
Platform: UNKNOWN
Requires-Dist: requests
Requires-Dist: requests-oauthlib
Requires-Dist: simplejson
